{"1": [[["frm_cogitation"], ["frm_categorization"], ["frm_coming_to_believe"]]], "2": [[["frm_cogitation"], ["frm_categorization"]]], "3": [[["frm_categorization"]]], "4": [[]], "5": [[["frm_cogitation"], ["frm_categorization"], ["frm_coming_to_believe"]]], "6": [[["frm_cogitation"], ["frm_categorization"], ["frm_coming_to_believe"]]], "7": [[["frm_cogitation"], ["frm_coming_to_believe"]]], "8": [[["frm_cogitation"], ["frm_categorization"], ["frm_coming_to_believe"]]], "9": [[["frm_cogitation"], ["frm_categorization"], ["frm_coming_to_believe"]]], "10": [[["frm_cogitation"], ["frm_categorization"], ["frm_coming_to_believe"]]], "11": [[["frm_cogitation"], ["frm_categorization"], ["frm_coming_to_believe"]]], "12": [[["frm_cogitation"], ["frm_categorization"]]], "13": [[["frm_cogitation"], ["frm_categorization"], ["frm_coming_to_believe"]]], "14": [[["frm_coming_to_believe"]]], "15": [[["frm_coming_to_believe"]]], "16": [[["frm_cogitation"], ["frm_categorization"], ["frm_coming_to_believe"]]], "17": [[["frm_cogitation"], ["frm_categorization"], ["frm_coming_to_believe"]]], "18": [[["frm_cogitation"], ["frm_categorization"], ["frm_coming_to_believe"]]], "19": [[["frm_cogitation"], ["frm_categorization"], ["frm_coming_to_believe"]]], "20": [[["frm_cogitation"], ["frm_categorization"], ["frm_coming_to_believe"]]], "21": [[["frm_cogitation"], ["frm_categorization"], ["frm_coming_to_believe"]]], "22": [[["frm_cogitation"], ["frm_categorization"], ["frm_coming_to_believe"]]], "23": [[["frm_cogitation"], ["frm_categorization"], ["frm_coming_to_believe"]]], "24": [[["frm_cogitation"], ["frm_categorization"], ["frm_coming_to_believe"]]], "25": [[["frm_cogitation"], ["frm_categorization"], ["frm_coming_to_believe"]]], "26": [[["frm_cogitation"], ["frm_categorization"], ["frm_coming_to_believe"]]], "27": [[["frm_cogitation"], ["frm_categorization"], ["frm_coming_to_believe"]]], "28": [[["frm_cogitation"], ["frm_categorization"], ["frm_coming_to_believe"]]], "29": [[["frm_cogitation"], ["frm_categorization"], ["frm_coming_to_believe"]]], "30": [[["frm_cogitation"], ["frm_categorization"], ["frm_coming_to_believe"]]], "31": [[["frm_cogitation"], ["frm_categorization"], ["frm_coming_to_believe"]]], "32": [[["frm_cogitation"], ["frm_categorization"], ["frm_coming_to_believe"]]], "33": [[["frm_cogitation"], ["frm_categorization"], ["frm_coming_to_believe"]]], "34": [[["frm_cogitation"], ["frm_categorization"], ["frm_coming_to_believe"]]], "35": [[["frm_cogitation"], ["frm_categorization"], ["frm_coming_to_believe"]]], "36": [[["frm_cogitation"], ["frm_categorization"], ["frm_coming_to_believe"]]], "37": [[["frm_cogitation"], ["frm_categorization"], ["frm_coming_to_believe"]]], "38": [[["frm_cogitation"], ["frm_categorization"], ["frm_coming_to_believe"]]], "39": [[["frm_cogitation"], ["frm_categorization"], ["frm_coming_to_believe"]]], "40": [[["frm_cogitation"], ["frm_categorization"], ["frm_coming_to_believe"]]], "41": [[["frm_cogitation"], ["frm_categorization"], ["frm_coming_to_believe"]]], "42": [[["frm_cogitation"], ["frm_categorization"], ["frm_coming_to_believe"]]], "43": [[["frm_cogitation"], ["frm_categorization"], ["frm_coming_to_believe"]]], "44": [[["frm_cogitation"], ["frm_categorization"], ["frm_coming_to_believe"]]], "45": [[["frm_cogitation"]]], "46": [[["frm_cogitation"]]], "47": [[["frm_cogitation"]]], "48": [[["frm_cogitation"]]], "49": [[["frm_cogitation"]]], "50": [[["frm_cogitation"]]], "51": [[["frm_cogitation"]]], "52": [[["frm_cogitation"]]], "53": [[["frm_cogitation"]]], "54": [[["frm_cogitation"]]], "55": [[["frm_cogitation"]]], "56": [[["frm_cogitation"]]], "57": [[["frm_cogitation"]]], "58": [[["frm_cogitation"]]], "59": [[["frm_cogitation"]]], "60": [[["frm_cogitation"]]], "61": [[["frm_cogitation"]]], "62": [[["frm_cogitation"]]], "63": [[["frm_cogitation"]]], "64": [[["frm_cogitation"]]], "65": [[["frm_cogitation"]]], "66": [[["frm_cogitation"]]], "67": [[["frm_cogitation"]]], "68": [[["frm_cogitation"]]], "69": [[["frm_cogitation"]]], "70": [[["frm_cogitation"]]], "71": [[["frm_cogitation"]]], "72": [[["frm_cogitation"]]], "73": [[["frm_cogitation"]]], "74": [[["frm_cogitation"], ["frm_categorization"], ["frm_coming_to_believe"]]], "75": [[["frm_cogitation"], ["frm_categorization"], ["frm_coming_to_believe"]]]}{"1": [["frm_cogitation"]], "2": [], "3": [], "4": [], "5": [], "6": [], "7": [], "8": [["frm_categorization"]], "9": [], "10": [], "11": [], "12": [], "13": [], "14": [], "15": [], "16": [["frm_cogitation"]], "17": [], "18": [], "19": [], "20": [], "21": [], "22": [], "23": [], "24": [], "25": [], "26": [], "27": [], "28": [], "29": [], "30": [], "31": [], "32": [], "33": [], "34": [], "35": [], "36": [], "37": [], "38": [], "39": [], "40": [], "41": [], "42": [], "43": [], "44": [], "45": [], "46": [], "47": [], "48": [], "49": [], "50": [], "51": [], "52": [], "53": [], "54": [], "55": [], "56": [], "57": [], "58": [], "59": [], "60": [], "61": [], "62": [], "63": [], "64": [], "65": [], "66": [], "67": [], "68": [], "69": [], "70": [], "71": [], "72": [], "73": [], "74": [], "75": []}